setup.py
nlutils/CommonDefine.py
nlutils/Defines.py
nlutils/__init__.py
nlutils.egg-info/PKG-INFO
nlutils.egg-info/SOURCES.txt
nlutils.egg-info/dependency_links.txt
nlutils.egg-info/requires.txt
nlutils.egg-info/top_level.txt
nlutils/TrainingManager/ParameterWatcher.py
nlutils/TrainingManager/TrainingManager.py
nlutils/TrainingManager/WeChatAssistant.py
nlutils/TrainingManager/__init__.py
nlutils/Utils/EmailUtils.py
nlutils/Utils/Exception.py
nlutils/Utils/Log.py
nlutils/Utils/SocketStore.py
nlutils/Utils/__init__.py