Metadata-Version: 2.1
Name: nlutils
Version: 0.0.19
Summary: Toolkit for neural learning training
Home-page: UNKNOWN
Author: Nikola Liu
Author-email: nikolaliu@icloud.com
License: UNKNOWN
Platform: UNKNOWN
